{"cameraMode":{"drawMode":0,"name":"Shaded","section":"Shading Mode"},"sceneLighting":true,"audioPlay":false,"sceneViewState":{"showFog":true,"showMaterialUpdate":false,"showSkybox":true,"showFlares":true,"showImageEffects":true,"showParticleSystems":true},"in2DMode":false,"pivot":{"x":16.4464168548584,"y":-5.586429595947266,"z":2.763766288757324},"rotation":{"x":-0.48523595929145815,"y":0.5128167271614075,"z":-0.531010091304779,"w":-0.46860796213150027},"size":72.73921203613281,"orthographic":false}